github_discussions/__init__.py
github_discussions/async_client.py
github_discussions/base_client.py
github_discussions/client.py
github_discussions/exceptions.py
github_discussions-0.1.1.dist-info/licenses/LICENSE
github_discussions-0.1.1.dist-info/METADATA
github_discussions-0.1.1.dist-info/WHEEL
github_discussions-0.1.1.dist-info/top_level.txt
github_discussions-0.1.1.dist-info/RECORD
