Metadata-Version: 2.4
Name: github-discussions
Version: 0.1.1
Summary: A Python package for interacting with GitHub Discussions using GraphQL API
Home-page: https://github.com/Declytic/github-discussions-graphql
Author: Bill Schumacher
Author-email: Bill Schumacher <34168009+BillSchumacher@users.noreply.github.com>
Maintainer-email: Bill Schumacher <34168009+BillSchumacher@users.noreply.github.com>
License: MIT License
Project-URL: Homepage, https://github.com/Declytic/github-discussions
Project-URL: Documentation, https://github.com/Declytic/github-discussionsl#readme
Project-URL: Repository, https://github.com/Declytic/github-discussions.git
Project-URL: Issues, https://github.com/Declytic/github-discussions/issues
Project-URL: Changelog, https://github.com/Declytic/github-discussions/blob/main/CHANGELOG.md
Keywords: github,graphql,discussions,api,python
Classifier: Development Status :: 3 - Alpha
Classifier: Intended Audience :: Developers
Classifier: License :: OSI Approved :: MIT License
Classifier: Operating System :: OS Independent
Classifier: Programming Language :: Python :: 3
Classifier: Programming Language :: Python :: 3.8
Classifier: Programming Language :: Python :: 3.9
Classifier: Programming Language :: Python :: 3.10
Classifier: Programming Language :: Python :: 3.11
Classifier: Programming Language :: Python :: 3.12
Classifier: Topic :: Software Development :: Libraries :: Python Modules
Classifier: Topic :: Internet :: WWW/HTTP :: Dynamic Content
Requires-Python: >=3.8
License-File: LICENSE
Requires-Dist: requests>=2.25.0
Requires-Dist: typing-extensions>=4.0.0
Requires-Dist: pydantic>=2.0.0
Requires-Dist: aiohttp>=3.8.0
Provides-Extra: dev
Requires-Dist: pytest>=7.0.0; extra == "dev"
Requires-Dist: pytest-asyncio>=0.21.0; extra == "dev"
Requires-Dist: black>=22.0.0; extra == "dev"
Requires-Dist: isort>=5.10.0; extra == "dev"
Requires-Dist: flake8>=4.0.0; extra == "dev"
Requires-Dist: mypy>=1.0.0; extra == "dev"
Requires-Dist: sphinx>=5.0.0; extra == "dev"
Requires-Dist: sphinx-rtd-theme>=1.2.0; extra == "dev"
Requires-Dist: pre-commit>=3.0.0; extra == "dev"
Requires-Dist: bandit>=1.7.0; extra == "dev"
Requires-Dist: safety>=2.0.0; extra == "dev"
Requires-Dist: types-requests>=2.25.0; extra == "dev"
Provides-Extra: test
Requires-Dist: pytest>=7.0.0; extra == "test"
Requires-Dist: pytest-asyncio>=0.21.0; extra == "test"
Requires-Dist: pytest-cov>=4.0.0; extra == "test"
Dynamic: author
Dynamic: home-page
Dynamic: license-file
Dynamic: requires-python
